[
   {
      "nombre":"C.C. Alfares",
      "horas":[
         "07:30",
         "07:50",
         "08:10",
         "08:30",
         "08:50",
         "09:10",
         "09:30",
         "09:50",
         "10:10",
         "10:30",
         "10:50",
         "11:10",
         "11:30",
         "11:50",
         "12:10",
         "12:30",
         "12:50",
         "13:10",
         "13:30",
         "13:50",
         "14:10",
         "14:30",
         "14:50",
         "15:10",
         "15:30",
         "15:50",
         "16:10",
         "16:30",
         "16:50",
         "17:10",
         "17:30",
         "17:50",
         "18:10",
         "18:30",
         "18:50",
         "19:10",
         "19:30",
         "19:50",
         "20:10",
         "20:30",
         "20:50",
         "21:10",
         "21:30",
         "21:50",
         "22:10"
      ],
      "coordenada":"39.9644682,-4.7989729"
   },
   {
      "nombre":"Talavera Golf",
      "horas":[
         "07:31",
         "07:51",
         "08:11",
         "08:31",
         "08:51",
         "09:11",
         "09:31",
         "09:51",
         "10:11",
         "10:31",
         "10:51",
         "11:11",
         "11:31",
         "11:50",
         "12:11",
         "12:31",
         "12:51",
         "13:11",
         "13:31",
         "13:51",
         "14:11",
         "14:31",
         "14:51",
         "15:11",
         "15:31",
         "15:51",
         "16:11",
         "16:31",
         "16:51",
         "17:11",
         "17:31",
         "17:51",
         "18:11",
         "18:31",
         "18:51",
         "19:11",
         "19:31",
         "19:51",
         "20:11",
         "20:31",
         "20:51",
         "21:11",
         "21:31",
         "21:51",
         "22:11"
      ],
      "coordenada":"39.9648937,-4.7982005"
   },
   {
      "nombre":"Parque Comercial",
      "horas":[
         "07:32",
         "07:52",
         "08:12",
         "08:32",
         "08:52",
         "09:12",
         "09:32",
         "09:52",
         "10:12",
         "10:32",
         "10:41",
         "11:12",
         "11:32",
         "11:52",
         "12:12",
         "12:32",
         "12:52",
         "13:12",
         "13:32",
         "13:52",
         "14:12",
         "14:32",
         "14:52",
         "15:12",
         "15:32",
         "15:52",
         "16:12",
         "16:32",
         "16:52",
         "17:12",
         "17:32",
         "17:51",
         "18:12",
         "18:32",
         "18:52",
         "19:12",
         "19:32",
         "19:52",
         "20:12",
         "20:32",
         "20:52",
         "21:12",
         "21:32",
         "21:52",
         "22:12"
      ],
      "coordenada":"39.9643551 , -4.8020807"
   },
   {
      "nombre":"I.E.S P. Juan de Mariana",
      "horas":[
         "14:34"
      ],
      "coordenada":"39.9615037,-4.8046933"
   },
   {
      "nombre":"Hospital",
      "horas":[
         "07:33",
         "07:53",
         "08:13",
         "08:33",
         "08:53",
         "09:13",
         "09:33",
         "09:53",
         "10:13",
         "10:33",
         "10:23",
         "11:13",
         "11:33",
         "11:53",
         "12:13",
         "12:33",
         "12:53",
         "13:13",
         "13:33",
         "13:53",
         "14:13",
         "14:33",
         "14:53",
         "15:13",
         "15:33",
         "15:53",
         "16:13",
         "16:33",
         "16:53",
         "17:13",
         "17:33",
         "17:53",
         "18:13",
         "18:33",
         "18:53",
         "19:13",
         "19:33",
         "19:53",
         "20:13",
         "20:33",
         "20:53",
         "21:13",
         "21:33",
         "21:53",
         "22:13"
      ],
      "coordenada":"39.9635883,-4.8078618"
   },
   {
      "nombre":"Pablo Picasso",
      "horas":[
         "07:35",
         "07:55",
         "08:15",
         "08:35",
         "08:55",
         "09:15",
         "09:35",
         "09:55",
         "10:15",
         "10:35",
         "10:25",
         "11:15",
         "11:35",
         "11:55",
         "12:15",
         "12:35",
         "12:55",
         "13:15",
         "13:35",
         "13:55",
         "14:15",
         "14:35",
         "14:55",
         "15:15",
         "15:35",
         "15:55",
         "16:15",
         "16:35",
         "16:55",
         "17:15",
         "17:35",
         "17:55",
         "18:15",
         "18:35",
         "18:55",
         "19:15",
         "19:35",
         "19:55",
         "20:15",
         "20:35",
         "20:55",
         "21:15",
         "21:35",
         "21:55",
         "22:15"
      ],
      "coordenada":"39.9645865,-4.8122432"
   },
   {
      "nombre":"Nuevo Centro",
      "horas":[
         "07:36",
         "07:56",
         "08:16",
         "08:36",
         "08:56",
         "09:16",
         "09:36",
         "09:56",
         "10:16",
         "10:36",
         "10:26",
         "11:16",
         "11:36",
         "11:56",
         "12:16",
         "12:36",
         "12:56",
         "13:16",
         "13:36",
         "13:56",
         "14:16",
         "14:36",
         "14:56",
         "15:16",
         "15:36",
         "15:56",
         "16:16",
         "16:36",
         "16:56",
         "17:16",
         "17:36",
         "17:56",
         "18:16",
         "18:36",
         "18:56",
         "19:16",
         "19:36",
         "19:56",
         "20:16",
         "20:36",
         "20:56",
         "21:16",
         "21:36",
         "21:56",
         "22:16"
      ],
      "coordenada":"39.9659174,-4.813562"
   },
   {
      "nombre":"Polideportivo 1º Mayo",
      "horas":[
         "07:37",
         "07:57",
         "08:17",
         "08:37",
         "08:57",
         "09:17",
         "09:37",
         "09:57",
         "10:17",
         "10:37",
         "10:27",
         "11:17",
         "11:37",
         "11:57",
         "12:17",
         "12:37",
         "12:57",
         "13:17",
         "13:37",
         "13:57",
         "14:17",
         "14:37",
         "14:57",
         "15:17",
         "15:37",
         "15:57",
         "16:17",
         "16:37",
         "16:57",
         "17:17",
         "17:37",
         "17:57",
         "18:17",
         "18:37",
         "18:57",
         "19:17",
         "19:37",
         "19:57",
         "20:17",
         "20:37",
         "20:57",
         "21:17",
         "21:37",
         "21:57",
         "22:17"
      ],
      "coordenada":"39.9664855,-4.8153118"
   },
   {
      "nombre":"Ambulatorio M.Ortega",
      "horas":[
         "07:37",
         "07:57",
         "08:17",
         "08:37",
         "08:57",
         "09:17",
         "09:37",
         "09:57",
         "10:17",
         "10:37",
         "10:27",
         "11:17",
         "11:37",
         "11:57",
         "12:17",
         "12:37",
         "12:57",
         "13:17",
         "13:37",
         "13:57",
         "14:17",
         "14:37",
         "14:57",
         "15:17",
         "15:37",
         "15:57",
         "16:17",
         "16:37",
         "16:57",
         "17:17",
         "17:37",
         "17:57",
         "18:17",
         "18:37",
         "18:57",
         "19:17",
         "19:37",
         "19:57",
         "20:17",
         "20:37",
         "20:57",
         "21:17",
         "21:37",
         "21:57",
         "22:17"
      ],
      "coordenada":"39.9653027,-4.8173828"
   },
   {
      "nombre":"Plaza de la Paz",
      "horas":[
         "07:38",
         "07:58",
         "08:18",
         "08:38",
         "08:58",
         "09:18",
         "09:38",
         "09:58",
         "10:18",
         "10:38",
         "10:28",
         "11:18",
         "11:38",
         "11:58",
         "12:18",
         "12:38",
         "12:58",
         "13:18",
         "13:38",
         "13:58",
         "14:18",
         "14:38",
         "14:58",
         "15:18",
         "15:38",
         "15:58",
         "16:18",
         "16:38",
         "16:58",
         "17:18",
         "17:38",
         "17:58",
         "18:18",
         "18:38",
         "18:58",
         "19:18",
         "19:38",
         "19:58",
         "20:18",
         "20:38",
         "20:58",
         "21:18",
         "21:38",
         "21:58",
         "22:18"
      ],
      "coordenada":"39.9641557,-4.819626"
   },
   {
      "nombre":"Institutos",
      "horas":[
         "07:39",
         "07:59",
         "08:19",
         "08:39",
         "08:59",
         "09:19",
         "09:39",
         "09:59",
         "10:19",
         "10:39",
         "10:29",
         "11:19",
         "11:39",
         "11:59",
         "12:19",
         "12:39",
         "12:59",
         "13:19",
         "13:39",
         "13:59",
         "14:19",
         "14:39",
         "14:59",
         "15:19",
         "15:39",
         "15:59",
         "16:19",
         "16:39",
         "16:59",
         "17:19",
         "17:39",
         "17:59",
         "18:19",
         "18:39",
         "18:59",
         "19:19",
         "19:39",
         "19:59",
         "20:19",
         "20:39",
         "20:59",
         "21:19",
         "21:39",
         "21:59",
         "22:19"
      ],
      "coordenada":"39.964168,-4.8221043"
   },
   {
      "nombre":"Plaza España",
      "horas":[
         "07:41",
         "07:01",
         "08:21",
         "08:41",
         "08:01",
         "09:21",
         "09:41",
         "09:01",
         "10:21",
         "10:41",
         "10:01",
         "11:21",
         "11:41",
         "11:01",
         "12:21",
         "12:41",
         "12:01",
         "13:21",
         "13:41",
         "13:01",
         "14:21",
         "14:41",
         "14:01",
         "15:21",
         "15:41",
         "15:01",
         "16:21",
         "16:41",
         "16:01",
         "17:21",
         "17:41",
         "17:01",
         "18:21",
         "18:41",
         "18:01",
         "19:21",
         "19:41",
         "19:01",
         "20:21",
         "20:41",
         "20:01",
         "21:21",
         "21:41",
         "21:01",
         "22:21"
      ],
      "coordenada":"39.9639604,-4.8258012"
   },
   {
      "nombre":"Biblioteca J. Hierro",
      "horas":[
         "07:41",
         "07:01",
         "08:21",
         "08:41",
         "08:01",
         "09:21",
         "09:41",
         "09:01",
         "10:21",
         "10:41",
         "10:01",
         "11:21",
         "11:41",
         "11:01",
         "12:21",
         "12:41",
         "12:01",
         "13:21",
         "13:41",
         "13:01",
         "14:21",
         "14:41",
         "14:01",
         "15:21",
         "15:41",
         "15:01",
         "16:21",
         "16:41",
         "16:01",
         "17:21",
         "17:41",
         "17:01",
         "18:21",
         "18:41",
         "18:01",
         "19:21",
         "19:41",
         "19:01",
         "20:21",
         "20:41",
         "20:01",
         "21:21",
         "21:41",
         "21:01",
         "22:21"
      ],
      "coordenada":"39.963742,-4.8250479"
   },
   {
      "nombre":"Estanción Autobuses",
      "horas":[
         "07:42",
         "08:02",
         "08:22",
         "08:42",
         "09:02",
         "09:22",
         "09:42",
         "10:02",
         "10:22",
         "10:42",
         "11:02",
         "11:22",
         "11:42",
         "12:02",
         "12:22",
         "12:42",
         "13:02",
         "13:22",
         "13:42",
         "14:02",
         "14:22",
         "14:42",
         "15:02",
         "15:22",
         "15:42",
         "16:02",
         "16:22",
         "16:42",
         "17:02",
         "17:22",
         "17:42",
         "18:02",
         "18:22",
         "18:42",
         "19:02",
         "19:22",
         "19:42",
         "20:02",
         "20:22",
         "20:42",
         "21:02",
         "21:22",
         "21:42",
         "22:02",
         "22:22"
      ],
      "coordenada":"39.9621468,-4.8256318"
   },
   {
      "nombre":"Verjas del Prado",
      "horas":[
         "07:43",
         "08:03",
         "08:23",
         "08:43",
         "09:03",
         "09:23",
         "09:43",
         "10:03",
         "10:23",
         "10:43",
         "11:03",
         "11:23",
         "11:43",
         "12:03",
         "12:23",
         "12:43",
         "13:03",
         "13:23",
         "13:43",
         "14:03",
         "14:23",
         "14:43",
         "15:03",
         "15:23",
         "15:43",
         "16:03",
         "16:23",
         "16:43",
         "17:03",
         "17:23",
         "17:43",
         "18:03",
         "18:23",
         "18:43",
         "19:03",
         "19:23",
         "19:43",
         "20:03",
         "20:23",
         "20:43",
         "21:03",
         "21:23",
         "21:43",
         "22:03",
         "22:23"
      ],
      "coordenada":"39.9603858,-4.8255702 "
   },
   {
      "nombre":"Ronda del Cañillo",
      "horas":[
         "07:44",
         "08:04",
         "08:24",
         "08:44",
         "09:04",
         "09:24",
         "09:44",
         "10:04",
         "10:24",
         "10:44",
         "11:04",
         "11:24",
         "11:44",
         "12:04",
         "12:24",
         "12:44",
         "13:04",
         "13:24",
         "13:44",
         "14:04",
         "14:24",
         "14:44",
         "15:04",
         "15:24",
         "15:44",
         "16:04",
         "16:24",
         "16:44",
         "17:04",
         "17:24",
         "17:44",
         "18:04",
         "18:24",
         "18:44",
         "19:04",
         "19:24",
         "19:44",
         "20:04",
         "20:24",
         "20:44",
         "21:04",
         "21:24",
         "21:44",
         "22:04",
         "22:24"
      ],
      "coordenada":"39.958543,-4.8272583"
   },
   {
      "nombre":"Carnicerías",
      "horas":[
         "07:46",
         "08:06",
         "08:26",
         "08:46",
         "09:06",
         "09:26",
         "09:46",
         "10:06",
         "10:26",
         "10:46",
         "11:06",
         "11:26",
         "11:46",
         "12:06",
         "12:26",
         "12:46",
         "13:06",
         "13:26",
         "13:46",
         "14:06",
         "14:26",
         "14:46",
         "15:06",
         "15:26",
         "15:46",
         "16:06",
         "16:26",
         "16:46",
         "17:06",
         "17:26",
         "17:46",
         "18:06",
         "18:26",
         "18:46",
         "19:06",
         "19:26",
         "19:46",
         "20:06",
         "20:26",
         "20:46",
         "21:06",
         "21:26",
         "21:46",
         "22:06",
         "22:26"
      ],
      "coordenada":"39.9595057,-4.8290446 "
   },
   {
      "nombre":"Plaza del Reloj",
      "horas":[
         "07:47",
         "08:07",
         "08:27",
         "08:47",
         "09:07",
         "09:27",
         "09:47",
         "10:07",
         "10:27",
         "10:47",
         "11:07",
         "11:27",
         "11:47",
         "12:07",
         "12:27",
         "12:47",
         "13:07",
         "13:27",
         "13:47",
         "14:07",
         "14:27",
         "14:47",
         "15:07",
         "15:27",
         "15:47",
         "16:07",
         "16:27",
         "16:47",
         "17:07",
         "17:27",
         "17:47",
         "18:07",
         "18:27",
         "18:47",
         "19:07",
         "19:27",
         "19:47",
         "20:07",
         "20:27",
         "20:47",
         "21:07",
         "21:27",
         "21:47",
         "22:07",
         "22:27"
      ],
      "coordenada":"39.9602924,-4.831683"
   },
   {
      "nombre":"Palenque",
      "horas":[
         "07:48",
         "08:08",
         "08:28",
         "08:48",
         "09:08",
         "09:28",
         "09:48",
         "10:08",
         "10:28",
         "10:48",
         "11:08",
         "11:28",
         "11:48",
         "12:08",
         "12:28",
         "12:48",
         "13:08",
         "13:28",
         "13:48",
         "14:08",
         "14:28",
         "14:48",
         "15:08",
         "15:28",
         "15:48",
         "16:08",
         "16:28",
         "16:48",
         "17:08",
         "17:28",
         "17:48",
         "18:08",
         "18:28",
         "18:48",
         "19:08",
         "19:28",
         "19:48",
         "20:08",
         "20:28",
         "20:48",
         "21:08",
         "21:28",
         "21:48",
         "22:08",
         "22:28"
      ],
      "coordenada":"39.9600277,-4.833588"
   },
   {
      "nombre":"Puente Pópulo",
      "horas":[
         "07:49",
         "08:09",
         "08:29",
         "08:49",
         "09:09",
         "09:29",
         "09:49",
         "10:09",
         "10:29",
         "10:49",
         "11:09",
         "11:29",
         "11:49",
         "12:09",
         "12:29",
         "12:49",
         "13:09",
         "13:29",
         "13:49",
         "14:09",
         "14:29",
         "14:49",
         "15:09",
         "15:29",
         "15:49",
         "16:09",
         "16:29",
         "16:49",
         "17:09",
         "17:29",
         "17:49",
         "18:09",
         "18:29",
         "18:49",
         "19:09",
         "19:29",
         "19:49",
         "20:09",
         "20:29",
         "20:49",
         "21:09",
         "21:29",
         "21:49",
         "22:09",
         "22:29"
      ],
      "coordenada":"39.959791,-4.8357336"
   },
   {
      "nombre":"Plaza San Andrés",
      "horas":[
         "07:50",
         "08:10",
         "08:30",
         "08:50",
         "09:10",
         "09:30",
         "09:50",
         "10:10",
         "10:30",
         "10:50",
         "11:10",
         "11:30",
         "11:50",
         "12:10",
         "12:30",
         "12:50",
         "13:10",
         "13:30",
         "13:50",
         "14:10",
         "14:30",
         "14:50",
         "15:10",
         "15:30",
         "15:50",
         "16:10",
         "16:30",
         "16:50",
         "17:10",
         "17:30",
         "17:50",
         "18:10",
         "18:30",
         "18:50",
         "19:10",
         "19:30",
         "19:50",
         "20:10",
         "20:30",
         "20:50",
         "21:10",
         "21:30",
         "21:50",
         "22:10",
         "22:30"
      ],
      "coordenada":"39.9590049,-4.8378261"
   },
   {
      "nombre":"Puerta de Cuartos",
      "horas":[
         "07:51",
         "08:11",
         "08:31",
         "08:51",
         "09:11",
         "09:31",
         "09:51",
         "10:11",
         "10:31",
         "10:51",
         "11:11",
         "11:31",
         "11:51",
         "12:11",
         "12:31",
         "12:51",
         "13:11",
         "13:31",
         "13:51",
         "14:11",
         "14:31",
         "14:51",
         "15:11",
         "15:31",
         "15:51",
         "16:11",
         "16:31",
         "16:51",
         "17:11",
         "17:31",
         "17:51",
         "18:11",
         "18:31",
         "18:51",
         "19:11",
         "19:31",
         "19:51",
         "20:11",
         "20:31",
         "20:51",
         "21:11",
         "21:31",
         "21:51",
         "22:11",
         "22:31"
      ],
      "coordenada":"39.9586768,-4.839822 "
   },
   {
      "nombre":"Juan de Mariana",
      "horas":[
         "07:52",
         "08:12",
         "08:32",
         "08:52",
         "09:12",
         "09:32",
         "09:52",
         "10:12",
         "10:32",
         "10:52",
         "11:12",
         "11:32",
         "11:52",
         "12:12",
         "12:32",
         "12:52",
         "13:12",
         "13:32",
         "13:52",
         "14:12",
         "14:32",
         "14:52",
         "15:12",
         "15:32",
         "15:52",
         "16:12",
         "16:32",
         "16:52",
         "17:12",
         "17:32",
         "17:52",
         "18:12",
         "18:32",
         "18:52",
         "19:12",
         "19:32",
         "19:52",
         "20:12",
         "20:32",
         "20:52",
         "21:12",
         "21:32",
         "21:52",
         "22:12",
         "22:32"
      ],
      "coordenada":"39.9555516,-4.8391375"
   },
   {
      "nombre":"Escuela de idiomas",
      "horas":[
         "07:53",
         "08:13",
         "08:33",
         "08:53",
         "09:13",
         "09:33",
         "09:53",
         "10:13",
         "10:33",
         "10:53",
         "11:13",
         "11:33",
         "11:53",
         "12:13",
         "12:33",
         "12:53",
         "13:13",
         "13:33",
         "13:53",
         "14:13",
         "14:33",
         "14:53",
         "15:13",
         "15:33",
         "15:53",
         "16:13",
         "16:33",
         "16:53",
         "17:13",
         "17:33",
         "17:53",
         "18:13",
         "18:33",
         "18:53",
         "19:13",
         "19:33",
         "19:53",
         "20:13",
         "20:33",
         "20:53",
         "21:13",
         "21:33",
         "21:53",
         "22:13",
         "22:33"
      ],
      "coordenada":"39.9543726,-4.840214"
   },
   {
      "nombre":"Universidad",
      "horas":[
         "07:54",
         "08:14",
         "08:34",
         "08:54",
         "09:14",
         "09:34",
         "09:54",
         "10:14",
         "10:34",
         "10:54",
         "11:14",
         "11:34",
         "11:54",
         "12:14",
         "12:34",
         "12:54",
         "13:14",
         "13:34",
         "13:54",
         "14:14",
         "14:34",
         "14:54",
         "15:14",
         "15:34",
         "15:54",
         "16:14",
         "16:34",
         "16:54",
         "17:14",
         "17:34",
         "17:54",
         "18:14",
         "18:34",
         "18:54",
         "19:14",
         "19:34",
         "19:54",
         "20:14",
         "20:34",
         "20:54",
         "21:14",
         "21:34",
         "21:54",
         "22:14",
         "22:34"
      ],
      "coordenada":"39.9537079,-4.8423128 "
   },
   {
      "nombre":"Polígono Marifé",
      "horas":[
         "07:56",
         "08:16",
         "08:36",
         "08:56",
         "09:16",
         "09:36",
         "09:56",
         "10:16",
         "10:36",
         "10:56",
         "11:16",
         "11:36",
         "11:56",
         "12:16",
         "12:36",
         "12:56",
         "13:16",
         "13:36",
         "13:56",
         "14:16",
         "14:36",
         "14:56",
         "15:16",
         "15:36",
         "15:56",
         "16:16",
         "16:36",
         "16:56",
         "17:16",
         "17:36",
         "17:56",
         "18:16",
         "18:36",
         "18:56",
         "19:16",
         "19:36",
         "19:56",
         "20:16",
         "20:36",
         "20:56",
         "21:16",
         "21:36",
         "21:56",
         "22:16",
         "22:36"
      ],
      "coordenada":"39.9550837,-4.8448931"
   },
   {
      "nombre":"Tanatorio",
      "horas":[
         "07:56",
         "08:16",
         "08:36",
         "08:56",
         "09:16",
         "09:36",
         "09:56",
         "10:16",
         "10:36",
         "10:56",
         "11:16",
         "11:36",
         "11:56",
         "12:16",
         "12:36",
         "12:56",
         "13:16",
         "13:36",
         "13:56",
         "14:16",
         "14:36",
         "14:56",
         "15:16",
         "15:36",
         "15:56",
         "16:16",
         "16:36",
         "16:56",
         "17:16",
         "17:36",
         "17:56",
         "18:16",
         "18:36",
         "18:56",
         "19:16",
         "19:36",
         "19:56",
         "20:16",
         "20:36",
         "20:56",
         "21:16",
         "21:36",
         "21:56",
         "22:16",
         "22:36"
      ],
      "coordenada":"39.9538281,-4.846702"
   },
   {
      "nombre":"Cementerio",
      "horas":[
         "07:57",
         "08:17",
         "08:37",
         "08:57",
         "09:17",
         "09:37",
         "09:57",
         "10:17",
         "10:37",
         "10:57",
         "11:17",
         "11:37",
         "11:57",
         "12:17",
         "12:37",
         "12:57",
         "13:17",
         "13:37",
         "13:57",
         "14:17",
         "14:37",
         "14:57",
         "15:17",
         "15:37",
         "15:57",
         "16:17",
         "16:37",
         "16:57",
         "17:17",
         "17:37",
         "17:57",
         "18:17",
         "18:37",
         "18:57",
         "19:17",
         "19:37",
         "19:57",
         "20:17",
         "20:37",
         "20:57",
         "21:17",
         "21:37",
         "21:57",
         "22:17",
         "22:37"
      ],
      "coordenada":"39.952488,-4.848984"
   },
   {
      "nombre":"Urb. Patrocinio",
      "horas":[
         "07:57",
         "08:17",
         "08:37",
         "08:57",
         "09:17",
         "09:37",
         "09:57",
         "10:17",
         "10:37",
         "10:57",
         "11:17",
         "11:37",
         "11:57",
         "12:17",
         "12:37",
         "12:57",
         "13:17",
         "13:37",
         "13:57",
         "14:17",
         "14:37",
         "14:57",
         "15:17",
         "15:37",
         "15:57",
         "16:17",
         "16:37",
         "16:57",
         "17:17",
         "17:37",
         "17:57",
         "18:17",
         "18:37",
         "18:57",
         "19:17",
         "19:37",
         "19:57",
         "20:17",
         "20:37",
         "20:57",
         "21:17",
         "21:37",
         "21:57",
         "22:17",
         "22:37"
      ],
      "coordenada":"39.9510046,-4.8522107"
   },
   {
      "nombre":"Residencia Patrocinio",
      "horas":[
         "11:00",
         "11:20",
         "13:20",
         "16:00",
         "16:20",
         "19:40"
      ],
      "coordenada":"39.950717, -4.857699"
   },
   {
      "nombre":"Patrocinio",
      "horas":[
         "07:59",
         "08:19",
         "08:39",
         "08:59",
         "09:19",
         "09:39",
         "09:59",
         "10:19",
         "10:39",
         "10:59",
         "11:19",
         "11:39",
         "11:59",
         "12:19",
         "12:39",
         "12:59",
         "13:19",
         "13:39",
         "13:59",
         "14:19",
         "14:39",
         "14:59",
         "15:19",
         "15:39",
         "15:59",
         "16:19",
         "16:39",
         "16:59",
         "17:19",
         "17:39",
         "17:59",
         "18:19",
         "18:39",
         "18:59",
         "19:19",
         "19:39",
         "19:59",
         "20:19",
         "20:39",
         "20:59",
         "21:19",
         "21:39",
         "21:59",
         "22:19",
         "22:39"
      ],
      "coordenada":"39.9514062,-4.8538038 "
   }
]
